[
 {
  "charts": [
   {
    "chart_name": "Receiving Trend",
    "label": "Receiving Trend",
    "parent": "Havano Abattoir",
    "parentfield": "charts",
    "parenttype": "Workspace"
   },
   {
    "chart_name": "Dispatch Trend",
    "label": "Dispatch Trend",
    "parent": "Havano Abattoir",
    "parentfield": "charts",
    "parenttype": "Workspace"
   },
   {
    "chart_name": "Dispatch Type Mix",
    "label": "Dispatch Type Mix",
    "parent": "Havano Abattoir",
    "parentfield": "charts",
    "parenttype": "Workspace"
   }
  ],
  "content": "[{\"id\":\"header_main\",\"type\":\"header\",\"data\":{\"text\":\"<span class=\\\"h4\\\"><b>Havano Abattoir Dashboard</b></span>\",\"col\":12}},{\"id\":\"shortcut_row\",\"type\":\"shortcut\",\"data\":{\"shortcut_name\":\"Received (Today)\",\"col\":4}},{\"id\":\"shortcut_row2\",\"type\":\"shortcut\",\"data\":{\"shortcut_name\":\"Received (This Week)\",\"col\":4}},{\"id\":\"shortcut_row3\",\"type\":\"shortcut\",\"data\":{\"shortcut_name\":\"Received (This Month)\",\"col\":4}},{\"id\":\"shortcut_row4\",\"type\":\"shortcut\",\"data\":{\"shortcut_name\":\"Dispatched (Today)\",\"col\":4}},{\"id\":\"shortcut_row5\",\"type\":\"shortcut\",\"data\":{\"shortcut_name\":\"Dispatched (This Week)\",\"col\":4}},{\"id\":\"shortcut_row6\",\"type\":\"shortcut\",\"data\":{\"shortcut_name\":\"Dispatched (This Month)\",\"col\":4}},{\"id\":\"chart_r\",\"type\":\"chart\",\"data\":{\"chart_name\":\"Receiving Trend\",\"col\":6}},{\"id\":\"chart_d\",\"type\":\"chart\",\"data\":{\"chart_name\":\"Dispatch Trend\",\"col\":6}},{\"id\":\"chart_pie\",\"type\":\"chart\",\"data\":{\"chart_name\":\"Dispatch Type Mix\",\"col\":12}},{\"id\":\"card_docs\",\"type\":\"card\",\"data\":{\"card_name\":\"Abattoir Documents\",\"col\":12}}]",
  "custom_blocks": [],
  "docstatus": 0,
  "doctype": "Workspace",
  "for_user": null,
  "hide_custom": 0,
  "icon": null,
  "indicator_color": "green",
  "is_hidden": 0,
  "label": "Havano Abattoir",
  "links": [
   {
    "dependencies": null,
    "description": null,
    "hidden": 0,
    "icon": null,
    "is_query_report": 0,
    "label": "Abattoir Documents",
    "link_count": 0,
    "link_to": null,
    "link_type": null,
    "onboard": 0,
    "only_for": null,
    "parent": "Havano Abattoir",
    "parentfield": "links",
    "parenttype": "Workspace",
    "report_ref_doctype": null,
    "type": "Card Break"
   },
   {
    "dependencies": null,
    "description": null,
    "hidden": 0,
    "icon": null,
    "is_query_report": 0,
    "label": "Receiving",
    "link_count": 0,
    "link_to": "Receiving",
    "link_type": "DocType",
    "onboard": 0,
    "only_for": null,
    "parent": "Havano Abattoir",
    "parentfield": "links",
    "parenttype": "Workspace",
    "report_ref_doctype": null,
    "type": "Link"
   },
   {
    "dependencies": null,
    "description": null,
    "hidden": 0,
    "icon": null,
    "is_query_report": 0,
    "label": "Processing",
    "link_count": 0,
    "link_to": "Processing",
    "link_type": "DocType",
    "onboard": 0,
    "only_for": null,
    "parent": "Havano Abattoir",
    "parentfield": "links",
    "parenttype": "Workspace",
    "report_ref_doctype": null,
    "type": "Link"
   },
   {
    "dependencies": null,
    "description": null,
    "hidden": 0,
    "icon": null,
    "is_query_report": 0,
    "label": "Brining",
    "link_count": 0,
    "link_to": "Brining",
    "link_type": "DocType",
    "onboard": 0,
    "only_for": null,
    "parent": "Havano Abattoir",
    "parentfield": "links",
    "parenttype": "Workspace",
    "report_ref_doctype": null,
    "type": "Link"
   },
   {
    "dependencies": null,
    "description": null,
    "hidden": 0,
    "icon": null,
    "is_query_report": 0,
    "label": "Storage",
    "link_count": 0,
    "link_to": "Storage",
    "link_type": "DocType",
    "onboard": 0,
    "only_for": null,
    "parent": "Havano Abattoir",
    "parentfield": "links",
    "parenttype": "Workspace",
    "report_ref_doctype": null,
    "type": "Link"
   }
  ],
  "modified": "2026-04-17 07:58:07.230976",
  "module": "Havano Abattoir",
  "name": "Havano Abattoir",
  "number_cards": [],
  "parent_page": null,
  "public": 1,
  "quick_lists": [],
  "restrict_to_domain": null,
  "roles": [],
  "sequence_id": 1.0,
  "shortcuts": [
   {
    "color": "Blue",
    "doc_view": null,
    "format": null,
    "icon": null,
    "kanban_board": null,
    "label": "Received (Today)",
    "link_to": "Receiving",
    "parent": "Havano Abattoir",
    "parentfield": "shortcuts",
    "parenttype": "Workspace",
    "report_ref_doctype": null,
    "restrict_to_domain": null,
    "stats_filter": "{\"date\": [\"timespan\", \"today\"], \"docstatus\": [\"!=\", 2]}",
    "type": "DocType",
    "url": null
   },
   {
    "color": "Blue",
    "doc_view": null,
    "format": null,
    "icon": null,
    "kanban_board": null,
    "label": "Received (This Week)",
    "link_to": "Receiving",
    "parent": "Havano Abattoir",
    "parentfield": "shortcuts",
    "parenttype": "Workspace",
    "report_ref_doctype": null,
    "restrict_to_domain": null,
    "stats_filter": "{\"date\": [\"timespan\", \"this week\"], \"docstatus\": [\"!=\", 2]}",
    "type": "DocType",
    "url": null
   },
   {
    "color": "Blue",
    "doc_view": null,
    "format": null,
    "icon": null,
    "kanban_board": null,
    "label": "Received (This Month)",
    "link_to": "Receiving",
    "parent": "Havano Abattoir",
    "parentfield": "shortcuts",
    "parenttype": "Workspace",
    "report_ref_doctype": null,
    "restrict_to_domain": null,
    "stats_filter": "{\"date\": [\"timespan\", \"this month\"], \"docstatus\": [\"!=\", 2]}",
    "type": "DocType",
    "url": null
   },
   {
    "color": "Green",
    "doc_view": null,
    "format": null,
    "icon": null,
    "kanban_board": null,
    "label": "Processing (Today)",
    "link_to": "Processing",
    "parent": "Havano Abattoir",
    "parentfield": "shortcuts",
    "parenttype": "Workspace",
    "report_ref_doctype": null,
    "restrict_to_domain": null,
    "stats_filter": "{\"date\": [\"timespan\", \"today\"], \"docstatus\": [\"!=\", 2]}",
    "type": "DocType",
    "url": null
   },
   {
    "color": "Green",
    "doc_view": null,
    "format": null,
    "icon": null,
    "kanban_board": null,
    "label": "Processing (This Week)",
    "link_to": "Processing",
    "parent": "Havano Abattoir",
    "parentfield": "shortcuts",
    "parenttype": "Workspace",
    "report_ref_doctype": null,
    "restrict_to_domain": null,
    "stats_filter": "{\"date\": [\"timespan\", \"this week\"], \"docstatus\": [\"!=\", 2]}",
    "type": "DocType",
    "url": null
   },
   {
    "color": "Green",
    "doc_view": null,
    "format": null,
    "icon": null,
    "kanban_board": null,
    "label": "Processing (This Month)",
    "link_to": "Processing",
    "parent": "Havano Abattoir",
    "parentfield": "shortcuts",
    "parenttype": "Workspace",
    "report_ref_doctype": null,
    "restrict_to_domain": null,
    "stats_filter": "{\"date\": [\"timespan\", \"this month\"], \"docstatus\": [\"!=\", 2]}",
    "type": "DocType",
    "url": null
   }
  ],
  "title": "Havano Abattoir Dashboard"
 },
 {
  "charts": [
   {
    "chart_name": "Receiving Trend",
    "label": "Receiving Trend",
    "parent": "Havano Abattoir Dashboard",
    "parentfield": "charts",
    "parenttype": "Workspace"
   },
   {
    "chart_name": "Dispatch Trend",
    "label": "Dispatch Trend",
    "parent": "Havano Abattoir Dashboard",
    "parentfield": "charts",
    "parenttype": "Workspace"
   },
   {
    "chart_name": "Dispatch Type Mix",
    "label": "Dispatch Type Mix",
    "parent": "Havano Abattoir Dashboard",
    "parentfield": "charts",
    "parenttype": "Workspace"
   }
  ],
  "content": "[{\"id\":\"header_main\",\"type\":\"header\",\"data\":{\"text\":\"<span class=\\\"h4\\\"><b>Havano Abattoir Dashboard</b></span>\",\"col\":12}},{\"id\":\"shortcut_row\",\"type\":\"shortcut\",\"data\":{\"shortcut_name\":\"Received (Today)\",\"col\":4}},{\"id\":\"shortcut_row2\",\"type\":\"shortcut\",\"data\":{\"shortcut_name\":\"Received (This Week)\",\"col\":4}},{\"id\":\"shortcut_row3\",\"type\":\"shortcut\",\"data\":{\"shortcut_name\":\"Received (This Month)\",\"col\":4}},{\"id\":\"shortcut_row4\",\"type\":\"shortcut\",\"data\":{\"shortcut_name\":\"Dispatched (Today)\",\"col\":4}},{\"id\":\"shortcut_row5\",\"type\":\"shortcut\",\"data\":{\"shortcut_name\":\"Dispatched (This Week)\",\"col\":4}},{\"id\":\"shortcut_row6\",\"type\":\"shortcut\",\"data\":{\"shortcut_name\":\"Dispatched (This Month)\",\"col\":4}},{\"id\":\"chart_r\",\"type\":\"chart\",\"data\":{\"chart_name\":\"Receiving Trend\",\"col\":6}},{\"id\":\"chart_d\",\"type\":\"chart\",\"data\":{\"chart_name\":\"Dispatch Trend\",\"col\":6}},{\"id\":\"chart_pie\",\"type\":\"chart\",\"data\":{\"chart_name\":\"Dispatch Type Mix\",\"col\":12}},{\"id\":\"card_docs\",\"type\":\"card\",\"data\":{\"card_name\":\"Abattoir Documents\",\"col\":12}}]",
  "custom_blocks": [],
  "docstatus": 0,
  "doctype": "Workspace",
  "for_user": null,
  "hide_custom": 0,
  "icon": null,
  "indicator_color": "green",
  "is_hidden": 0,
  "label": "Havano Abattoir Dashboard",
  "links": [
   {
    "dependencies": null,
    "description": null,
    "hidden": 0,
    "icon": null,
    "is_query_report": 0,
    "label": "Abattoir Documents",
    "link_count": 0,
    "link_to": null,
    "link_type": null,
    "onboard": 0,
    "only_for": null,
    "parent": "Havano Abattoir Dashboard",
    "parentfield": "links",
    "parenttype": "Workspace",
    "report_ref_doctype": null,
    "type": "Card Break"
   },
   {
    "dependencies": null,
    "description": null,
    "hidden": 0,
    "icon": null,
    "is_query_report": 0,
    "label": "Receiving",
    "link_count": 0,
    "link_to": "Receiving",
    "link_type": "DocType",
    "onboard": 0,
    "only_for": null,
    "parent": "Havano Abattoir Dashboard",
    "parentfield": "links",
    "parenttype": "Workspace",
    "report_ref_doctype": null,
    "type": "Link"
   },
   {
    "dependencies": null,
    "description": null,
    "hidden": 0,
    "icon": null,
    "is_query_report": 0,
    "label": "Processing",
    "link_count": 0,
    "link_to": "Processing",
    "link_type": "DocType",
    "onboard": 0,
    "only_for": null,
    "parent": "Havano Abattoir Dashboard",
    "parentfield": "links",
    "parenttype": "Workspace",
    "report_ref_doctype": null,
    "type": "Link"
   },
   {
    "dependencies": null,
    "description": null,
    "hidden": 0,
    "icon": null,
    "is_query_report": 0,
    "label": "Brining",
    "link_count": 0,
    "link_to": "Brining",
    "link_type": "DocType",
    "onboard": 0,
    "only_for": null,
    "parent": "Havano Abattoir Dashboard",
    "parentfield": "links",
    "parenttype": "Workspace",
    "report_ref_doctype": null,
    "type": "Link"
   },
   {
    "dependencies": null,
    "description": null,
    "hidden": 0,
    "icon": null,
    "is_query_report": 0,
    "label": "Storage",
    "link_count": 0,
    "link_to": "Storage",
    "link_type": "DocType",
    "onboard": 0,
    "only_for": null,
    "parent": "Havano Abattoir Dashboard",
    "parentfield": "links",
    "parenttype": "Workspace",
    "report_ref_doctype": null,
    "type": "Link"
   }
  ],
  "modified": "2026-04-17 07:58:07.230976",
  "module": "Havano Abattoir",
  "name": "Havano Abattoir Dashboard",
  "number_cards": [],
  "parent_page": null,
  "public": 1,
  "quick_lists": [],
  "restrict_to_domain": null,
  "roles": [],
  "sequence_id": 1.0,
  "shortcuts": [
   {
    "color": "Blue",
    "doc_view": null,
    "format": null,
    "icon": null,
    "kanban_board": null,
    "label": "Received (Today)",
    "link_to": "Receiving",
    "parent": "Havano Abattoir Dashboard",
    "parentfield": "shortcuts",
    "parenttype": "Workspace",
    "report_ref_doctype": null,
    "restrict_to_domain": null,
    "stats_filter": "{\"date\": [\"timespan\", \"today\"], \"docstatus\": [\"!=\", 2]}",
    "type": "DocType",
    "url": null
   },
   {
    "color": "Blue",
    "doc_view": null,
    "format": null,
    "icon": null,
    "kanban_board": null,
    "label": "Received (This Week)",
    "link_to": "Receiving",
    "parent": "Havano Abattoir Dashboard",
    "parentfield": "shortcuts",
    "parenttype": "Workspace",
    "report_ref_doctype": null,
    "restrict_to_domain": null,
    "stats_filter": "{\"date\": [\"timespan\", \"this week\"], \"docstatus\": [\"!=\", 2]}",
    "type": "DocType",
    "url": null
   },
   {
    "color": "Blue",
    "doc_view": null,
    "format": null,
    "icon": null,
    "kanban_board": null,
    "label": "Received (This Month)",
    "link_to": "Receiving",
    "parent": "Havano Abattoir Dashboard",
    "parentfield": "shortcuts",
    "parenttype": "Workspace",
    "report_ref_doctype": null,
    "restrict_to_domain": null,
    "stats_filter": "{\"date\": [\"timespan\", \"this month\"], \"docstatus\": [\"!=\", 2]}",
    "type": "DocType",
    "url": null
   },
   {
    "color": "Green",
    "doc_view": null,
    "format": null,
    "icon": null,
    "kanban_board": null,
    "label": "Processing (Today)",
    "link_to": "Processing",
    "parent": "Havano Abattoir Dashboard",
    "parentfield": "shortcuts",
    "parenttype": "Workspace",
    "report_ref_doctype": null,
    "restrict_to_domain": null,
    "stats_filter": "{\"date\": [\"timespan\", \"today\"], \"docstatus\": [\"!=\", 2]}",
    "type": "DocType",
    "url": null
   },
   {
    "color": "Green",
    "doc_view": null,
    "format": null,
    "icon": null,
    "kanban_board": null,
    "label": "Processing (This Week)",
    "link_to": "Processing",
    "parent": "Havano Abattoir Dashboard",
    "parentfield": "shortcuts",
    "parenttype": "Workspace",
    "report_ref_doctype": null,
    "restrict_to_domain": null,
    "stats_filter": "{\"date\": [\"timespan\", \"this week\"], \"docstatus\": [\"!=\", 2]}",
    "type": "DocType",
    "url": null
   },
   {
    "color": "Green",
    "doc_view": null,
    "format": null,
    "icon": null,
    "kanban_board": null,
    "label": "Processing (This Month)",
    "link_to": "Processing",
    "parent": "Havano Abattoir Dashboard",
    "parentfield": "shortcuts",
    "parenttype": "Workspace",
    "report_ref_doctype": null,
    "restrict_to_domain": null,
    "stats_filter": "{\"date\": [\"timespan\", \"this month\"], \"docstatus\": [\"!=\", 2]}",
    "type": "DocType",
    "url": null
   }
  ],
  "title": "Havano Abattoir Dashboard"
 }
]